ch5__48/ch5__48.srcs/sources_1/new/a.v

module mealy_fsm(
    input clk,
    input reset,
    input in,
    output reg out
);


    localparam A = 2'b00,
               B = 2'b01,
               C = 2'b10,
               D = 2'b11;

    reg [1:0] current_state, next_state;


    always @(posedge clk or posedge reset) begin
        if (reset)
            current_state <= A;
        else
            current_state <= next_state;
    end


    always @(*) begin
        case (current_state)
            A: begin
                if (in) begin
                    next_state = D;
                    out = 1'b0;
                end else begin
                    next_state = B;
                    out = 1'b1;
                end
            end
            B: begin
                if (in) begin
                    next_state = C;
                    out = 1'b1;
                end else begin
                    next_state = B;
                    out = 1'b0;
                end
            end
            C: begin
                if (in) begin
                    next_state = D;
                    out = 1'b1;
                end else begin
                    next_state = C;
                    out = 1'b0;
                end
            end
            D: begin
                if (in) begin
                    next_state = A;
                    out = 1'b0;
                end else begin
                    next_state = D;
                    out = 1'b0;
                end
            end
            default: begin
                next_state = A;
                out = 1'b0;
            end
        endcase
    end

endmodule

ch5__48/ch5__48.srcs/sim_1/new/aaas.v
`timescale 1ns/1ps

module mealy_fsm_tb();
    reg clk;
    reg reset;
    reg in;
    wire out;

    mealy_fsm uut (
        .clk(clk),
        .reset(reset),
        .in(in),
        .out(out)
    );

    initial begin
        clk = 0;
        forever #5 clk = ~clk;
    end

    initial begin
        $dumpfile("mealy_fsm_tb.vcd");
        $dumpvars(0, mealy_fsm_tb);

        reset = 1;
        in = 0;

        #10 reset = 0;

        #10 in = 0; // A -> B
        #10 in = 1; // B -> C
        #10 in = 1; // C -> D
        #10 in = 0; // D -> D
        #10 in = 1; // D -> A
        #10 in = 0; // A -> B

        #20 $finish;
    end
endmodule

ch5__48/ch5__48.sim/sim_1/behav/xsim/mealy_fsm_tb.vcd
$date
   Mon Nov 25 02:06:13 2024
$end

$version
  2024.1
  $dumpfile ("mealy_fsm_tb.vcd") 
$end

$timescale
  1ps
$end

$scope module mealy_fsm_tb $end
$var reg 1 ! clk $end
$var reg 1 " reset $end
$var reg 1 # in $end
$var wire 1 $ out $end
$scope module uut $end
$var wire 1 % clk $end
$var wire 1 & reset $end
$var wire 1 ' in $end
$var reg 1 ( out $end
$var reg 2 ) current_state [1:0] $end
$var reg 2 * next_state [1:0] $end
$upscope $end
$upscope $end
$enddefinitions $end

#0
$dumpvars
0!
1"
0#
1$
0%
1&
0'
1(
b0 )
b1 *
$end

#5000
1!
1%

#10000
0!
0"
0%
0&

#15000
1!
0$
1%
0(
b1 )

#20000
0!
0%

#25000
1!
1%

#30000
0!
1#
1$
0%
1'
1(
b10 *

#35000
1!
1%
b10 )
b11 *

#40000
0!
0%

#45000
1!
0$
1%
0(
b11 )
b0 *

#50000
0!
0#
0%
0'
b11 *

#55000
1!
1%

#60000
0!
1#
0%
1'
b0 *

#65000
1!
1%
b0 )
b11 *

#70000
0!
0#
1$
0%
0'
1(
b1 *

#75000
1!
0$
1%
0(
b1 )

